show_tree_path/tree.py
show_tree_path-0.3.dist-info/LICENSE
show_tree_path-0.3.dist-info/METADATA
show_tree_path-0.3.dist-info/WHEEL
show_tree_path-0.3.dist-info/top_level.txt
show_tree_path-0.3.dist-info/RECORD
